metropro_dat_reader/__init__.py
metropro_dat_reader/key.csv
metropro_dat_reader/main.py
metropro_dat_reader-0.1.1.dist-info/entry_points.txt
metropro_dat_reader-0.1.1.dist-info/WHEEL
metropro_dat_reader-0.1.1.dist-info/METADATA
metropro_dat_reader-0.1.1.dist-info/RECORD
