Metadata-Version: 2.1
Name: metropro-dat-reader
Version: 0.1.1
Summary: CLI utility to read metropro dat files
Author: Riley Shea
Author-email: riley.shea@liftbridgesw.com
Requires-Python: >=3.10,<4.0
Classifier: Programming Language :: Python :: 3
Classifier: Programming Language :: Python :: 3.10
